lsrec.py
lsrec-0.25.dist-info/METADATA
lsrec-0.25.dist-info/WHEEL
lsrec-0.25.dist-info/entry_points.txt
lsrec-0.25.dist-info/top_level.txt
lsrec-0.25.dist-info/RECORD
